[
   {
      "title" : "Main Sponsor",
      "logosClass" : "main",
      "logos" : [
         {
            "name" : "Google",
            "url" : "https://www.google.com.ua/intl/en/about/",
            "logoUrl" : "../images/logos/google.svg"
         }
      ]
   },
   {
    "logosClass" : "platinum",
      "logos" : [
         {
            "url" : "https://www.wearetriple.com/",
            "name" : "Triple",
            "logoUrl" : "../images/logos/triple.png"
         }
      ],
      "title" : "Platinum Sponsor"
   },
   {
      "title" : "Gold Sponsors",
      "logosClass" : "gold",
      "logos" : [
         {
            "name" : "Qualogy",
            "url" : "http://qualogy.com/devfest",
            "logoUrl" : "../images/logos/Logo_Qualogy_groot_RGB.jpg"
         },
         {
            "logoUrl" : "../images/logos/q42.png",
            "url" : "https://www.q42.nl",
            "name" : "Q42"
         },
         {
            "url" : "http://www.qlouder.com/",
            "name" : "Qlouder",
            "logoUrl" : "../images/logos/qlouder300.png"
         }
      ]
   },
   {
      "logosClass" : "silver",
      "logos" : [
         {
            "url" : "http://arnhem.luminis.eu/",
            "name" : "Luminis",
            "logoUrl" : "../images/logos/luminis-250.jpg"
         },
         {
            "url" : "https://www.m2mobi.com/",
            "name" : "M2Mobi",
            "logoUrl" : "../images/logos/m2mobi.svg"
         },
         {
            "name" : "Bol.com",
            "url" : "http://techlab.bol.com/",
            "logoUrl" : "../images/logos/bol-com.png"
         },
         {
            "name" : "UsMedia",
            "url" : "http://www.usmedia.nl",
            "logoUrl" : "../images/logos/UsMedia250.png"
         },
         {
            "url" : "https://www.bamtechmedia.com/",
            "name" : "Bamtech Media",
            "logoUrl" : "../images/logos/bamtechmedia-250.png"
         },
         {
            "url" : "https://www.nedap.com/",
            "name" : "Nedap",
            "logoUrl" : "../images/logos/nedap.png"
        }
      ],
      "title" : "Silver Sponsors"
   },
  {
    "logosClass" : "bronze",
    "logos" : [
      {
        "name" : "Code Orange",
        "url" : "https://code-orange.nl/",
        "logoUrl" : "../images/logos/co_logo.svg",
        "width" : "150px"
      }],
    "title" : "Bronze Sponsors"
  }
]
